LICENSE
README.md
setup.py
yaokong/__init__.py
yaokong/generators.py
yaokong/operation.py
yaokong/printers.py
yaokong/result.py
yaokong/run.py
yaokong/validate_inventory.py
yaokong.egg-info/PKG-INFO
yaokong.egg-info/SOURCES.txt
yaokong.egg-info/dependency_links.txt
yaokong.egg-info/requires.txt
yaokong.egg-info/top_level.txt
yaokong/operations/__init__.py
yaokong/operations/filesystem/__init__.py
yaokong/operations/filesystem/chown.py
yaokong/operations/filesystem/directory.py
yaokong/operations/generic/__init__.py
yaokong/operations/generic/a.py
yaokong/operations/generic/b.py
yaokong/operations/generic/c.py
yaokong/operations/generic/d.py