Metadata-Version: 2.4
Name: yaokong
Version: 0.1
Summary: A Python package for yaokong functionality
Author: Kim Jarvis
Author-email: kim.jarvis@tpfsystems.com
Requires-Python: >=3.6
License-File: LICENSE
Requires-Dist: setuptools
Requires-Dist: pytest
Requires-Dist: cryptography
Requires-Dist: bcrypt
Requires-Dist: asyncssh
Requires-Dist: black
Dynamic: author
Dynamic: author-email
Dynamic: license-file
Dynamic: requires-dist
Dynamic: requires-python
Dynamic: summary
